{
  "tablet-stand-adjustable": {
    "slug": "tablet-stand-adjustable",
    "store": "tech",
    "pid": "3052B795-EB62-41A2-8B3D-F97948B20132",
    "cjName": "360 Degree Spiral Base Lazy Mobile Phone Tablet Stand",
    "name": "Adjustable Tablet Stand",
    "description": "Hands-free viewing for recipes, video calls, and streaming.",
    "longDescription": "Prop tablets at the perfect angle on desks, kitchen counters, and nightstands. Adjustable hinge holds position for typing, drawing, or watching shows. Non-slip base keeps the stand steady on smooth surfaces. Ships from our US warehouse in 3–5 business days.",
    "features": [
      "Adjustable viewing angle",
      "Non-slip base",
      "Fits most tablet sizes",
      "Foldable portable design"
    ],
    "tags": [],
    "supplierSku": "CJSJSJSJ00008",
    "cjVid": "170D9F7D-7071-4E4A-A73E-CC5A3B66F020",
    "cjSku": "CJSJSJSJ00008-Black",
    "image": "https://cf.cjdropshipping.com/15139872/2105404712819.jpg",
    "images": [
      "https://cf.cjdropshipping.com/15139872/1133894694913.jpg",
      "https://cf.cjdropshipping.com/15139872/2336467600987.jpg",
      "https://cf.cjdropshipping.com/15139872/4587341175564.jpg",
      "https://oss-cf.cjdropshipping.com/product/2024/06/07/07/1c24d7fc-13e0-4625-93a9-a7292cd77c38.jpg",
      "https://cf.cjdropshipping.com/15139872/2105404712819.jpg",
      "https://cf.cjdropshipping.com/15139872/1290266577162.jpg",
      "https://cf.cjdropshipping.com/15139872/305513534996.jpg",
      "https://oss-cf.cjdropshipping.com/product/2024/06/07/07/2763a6e0-bb8f-4db5-8f4a-77df2d7ed3f1.jpg"
    ],
    "cost": 1.14,
    "shippingEst": 3.5,
    "price": 6.99,
    "compareAtPrice": 7.99,
    "listedNum": 6937,
    "rating": 4.9,
    "reviews": 36,
    "sold": 135
  }
}